default_shell.py
pshell.py
popotoshell-0.0.1.dist-info/METADATA
popotoshell-0.0.1.dist-info/WHEEL
popotoshell-0.0.1.dist-info/top_level.txt
popotoshell-0.0.1.dist-info/RECORD
